shachbuildsystemtest/__init__.py
shachbuildsystemtest-0.2.0.dist-info/WHEEL
shachbuildsystemtest-0.2.0.dist-info/METADATA
shachbuildsystemtest-0.2.0.dist-info/RECORD
